{
    "1": {
        "start": "2025-06-09T10:40:33.052611",
        "save_ckpt1": {
            "start": "2025-06-09T10:40:38.057688",
            "end": "2025-06-09T10:41:00.841863",
            "duration": 22.784175,
            "throughput": 4.595493195571014
        },
        "save_ckpt2": {
            "start": "2025-06-09T10:41:06.250120",
            "end": "2025-06-09T10:41:26.569535",
            "duration": 20.319415,
            "throughput": 5.1529299037004375
        },
        "save_ckpt3": {
            "start": "2025-06-09T10:41:34.588306",
            "end": "2025-06-09T10:41:54.006246",
            "duration": 19.41794,
            "throughput": 5.392153914328667
        },
        "save_ckpt4": {
            "start": "2025-06-09T10:42:02.192412",
            "end": "2025-06-09T10:42:24.538619",
            "duration": 22.346207,
            "throughput": 4.685561231004404
        },
        "save_ckpt5": {
            "start": "2025-06-09T10:42:29.639393",
            "end": "2025-06-09T10:42:48.435400",
            "duration": 18.796007,
            "throughput": 5.570572578484314
        },
        "save_ckpt6": {
            "start": "2025-06-09T10:42:57.196805",
            "end": "2025-06-09T10:43:19.320514",
            "duration": 22.123709,
            "throughput": 4.732683890354878
        },
        "save_ckpt7": {
            "start": "2025-06-09T10:43:24.890334",
            "end": "2025-06-09T10:43:46.515448",
            "duration": 21.625114,
            "throughput": 4.8418020445672205
        },
        "save_ckpt8": {
            "start": "2025-06-09T10:43:52.544168",
            "end": "2025-06-09T10:44:15.229597",
            "duration": 22.685429,
            "throughput": 4.615496633508638
        },
        "save_ckpt9": {
            "start": "2025-06-09T10:44:20.235791",
            "end": "2025-06-09T10:44:43.278741",
            "duration": 23.04295,
            "throughput": 4.543885274203139
        },
        "save_ckpt10": {
            "start": "2025-06-09T10:44:48.345850",
            "end": "2025-06-09T10:45:11.758119",
            "duration": 23.412269,
            "throughput": 4.4722073362133
        },
        "load_ckpt1": {
            "start": "2025-06-09T10:45:16.868034",
            "end": "2025-06-09T10:45:29.871335",
            "duration": 13.003301,
            "throughput": 8.052149310332755
        },
        "load_ckpt2": {
            "start": "2025-06-09T10:45:34.877587",
            "end": "2025-06-09T10:45:47.146160",
            "duration": 12.268573,
            "throughput": 8.534368355569896
        },
        "load_ckpt3": {
            "start": "2025-06-09T10:45:52.231264",
            "end": "2025-06-09T10:46:04.457817",
            "duration": 12.226553,
            "throughput": 8.563699121019573
        },
        "load_ckpt4": {
            "start": "2025-06-09T10:46:09.620138",
            "end": "2025-06-09T10:46:21.883473",
            "duration": 12.263335,
            "throughput": 8.538013613686589
        },
        "load_ckpt5": {
            "start": "2025-06-09T10:46:26.936520",
            "end": "2025-06-09T10:46:39.291379",
            "duration": 12.354859,
            "throughput": 8.474764558559448
        },
        "load_ckpt6": {
            "start": "2025-06-09T10:46:44.297588",
            "end": "2025-06-09T10:46:56.610128",
            "duration": 12.31254,
            "throughput": 8.503892875003794
        },
        "load_ckpt7": {
            "start": "2025-06-09T10:47:01.665257",
            "end": "2025-06-09T10:47:13.962348",
            "duration": 12.297091,
            "throughput": 8.514576429433532
        },
        "load_ckpt8": {
            "start": "2025-06-09T10:47:18.968562",
            "end": "2025-06-09T10:47:31.275754",
            "duration": 12.307192,
            "throughput": 8.507588179269423
        },
        "load_ckpt9": {
            "start": "2025-06-09T10:47:36.341961",
            "end": "2025-06-09T10:47:48.754386",
            "duration": 12.412425,
            "throughput": 8.435460530814826
        },
        "load_ckpt10": {
            "start": "2025-06-09T10:47:53.760558",
            "end": "2025-06-09T10:48:06.175649",
            "duration": 12.415091,
            "throughput": 8.433649111327433
        },
        "end": "2025-06-09T10:48:06.176785"
    }
}