{
    "1": {
        "start": "2025-06-04T18:31:20.080392",
        "save_ckpt1": {
            "start": "2025-06-04T18:31:25.085489",
            "end": "2025-06-04T18:32:17.654068",
            "duration": 52.568579,
            "throughput": 1.991770049161862
        },
        "save_ckpt2": {
            "start": "2025-06-04T18:32:23.148135",
            "end": "2025-06-04T18:33:16.077316",
            "duration": 52.929181,
            "throughput": 1.9782002895378112
        },
        "save_ckpt3": {
            "start": "2025-06-04T18:33:21.451110",
            "end": "2025-06-04T18:34:14.000586",
            "duration": 52.549476,
            "throughput": 1.9924941055396865
        },
        "save_ckpt4": {
            "start": "2025-06-04T18:34:19.325904",
            "end": "2025-06-04T18:35:04.202093",
            "duration": 44.876189,
            "throughput": 2.3331865631281485
        },
        "save_ckpt5": {
            "start": "2025-06-04T18:35:17.266421",
            "end": "2025-06-04T18:36:06.111955",
            "duration": 48.845534,
            "throughput": 2.143584328082056
        },
        "save_ckpt6": {
            "start": "2025-06-04T18:36:15.769510",
            "end": "2025-06-04T18:37:08.604570",
            "duration": 52.83506,
            "throughput": 1.9817242789011542
        },
        "save_ckpt7": {
            "start": "2025-06-04T18:37:14.164302",
            "end": "2025-06-04T18:38:06.705831",
            "duration": 52.541529,
            "throughput": 1.9927954738279356
        },
        "save_ckpt8": {
            "start": "2025-06-04T18:38:11.986655",
            "end": "2025-06-04T18:39:05.092192",
            "duration": 53.105537,
            "throughput": 1.9716309653209838
        },
        "save_ckpt9": {
            "start": "2025-06-04T18:39:10.112628",
            "end": "2025-06-04T18:39:54.894878",
            "duration": 44.78225,
            "throughput": 2.338080850765632
        },
        "save_ckpt10": {
            "start": "2025-06-04T18:40:07.891979",
            "end": "2025-06-04T18:41:00.262841",
            "duration": 52.370862,
            "throughput": 1.9992896274878809
        },
        "load_ckpt1": {
            "start": "2025-06-04T18:41:05.816299",
            "end": "2025-06-04T18:41:22.212496",
            "duration": 16.396197,
            "throughput": 6.38590285169172
        },
        "load_ckpt2": {
            "start": "2025-06-04T18:41:27.218775",
            "end": "2025-06-04T18:41:43.325987",
            "duration": 16.107212,
            "throughput": 6.500474519066318
        },
        "load_ckpt3": {
            "start": "2025-06-04T18:41:48.359166",
            "end": "2025-06-04T18:42:04.364785",
            "duration": 16.005619,
            "throughput": 6.5417351980700795
        },
        "load_ckpt4": {
            "start": "2025-06-04T18:42:09.399666",
            "end": "2025-06-04T18:42:25.360932",
            "duration": 15.961266,
            "throughput": 6.559913303819335
        },
        "load_ckpt5": {
            "start": "2025-06-04T18:42:30.367181",
            "end": "2025-06-04T18:42:45.529866",
            "duration": 15.162685,
            "throughput": 6.905407662244465
        },
        "load_ckpt6": {
            "start": "2025-06-04T18:42:51.355107",
            "end": "2025-06-04T18:43:07.327386",
            "duration": 15.972279,
            "throughput": 6.555390196928016
        },
        "load_ckpt7": {
            "start": "2025-06-04T18:43:12.333576",
            "end": "2025-06-04T18:43:26.222204",
            "duration": 13.888628,
            "throughput": 7.538867134982607
        },
        "load_ckpt8": {
            "start": "2025-06-04T18:43:33.366132",
            "end": "2025-06-04T18:43:49.102139",
            "duration": 15.736007,
            "throughput": 6.653817653944817
        },
        "load_ckpt9": {
            "start": "2025-06-04T18:43:54.391837",
            "end": "2025-06-04T18:44:10.385543",
            "duration": 15.993706,
            "throughput": 6.546607845561199
        },
        "load_ckpt10": {
            "start": "2025-06-04T18:44:15.394437",
            "end": "2025-06-04T18:44:30.923906",
            "duration": 15.529469,
            "throughput": 6.742311741579781
        },
        "end": "2025-06-04T18:44:30.925184"
    }
}